gh3.py
gh3-1.0.4.dist-info/WHEEL
gh3-1.0.4.dist-info/METADATA
gh3-1.0.4.dist-info/RECORD
